ram/DPRAM.v
module DPRAM 
 #(
   parameter data_width = 8,
   parameter addr_width = 10
  )

  (
   input wire clk,
   input wire we,
   input wire [(addr_width-1):0] wr_add, rd_add,
   input wire [(data_width-1):0] d,
   output wire [(data_width-1):0] q
  );

  reg [(data_width-1):0] ram [(2**addr_width)-1:0]; // must be written reg [(data_width-1):0] ram [0:(2**addr_width)-1];
  reg [(data_width-1):0] data_reg;

  initial 
    $readmemb("initialRAM.txt", ram);
    
  always @(posedge clk)
  begin
    if (we)  
      ram[wr_add] <= d;
    data_reg <= ram[rd_add];
  end
  assign q = data_reg;
endmodule

ram/DPRAM_tb.v
`timescale 1ns/1ns
module DPRAM_tb;
 reg clk;
 reg we;
 reg [9:0] wr_add, rd_add;
 reg [7:0] d;
 wire [7:0]q;

DPRAM circ1(clk, we, wr_add, rd_add, d, q);

always 
 begin
    clk=~clk;
    #10;
 end

initial begin
 $dumpfile("test.vcd");
 $dumpvars(0, DPRAM_tb);
    
    clk<= 0;
    we <= 0;
    //rd_add <= 2'b00;
    //wr_add <= 2'b00;
    //d <= 8'b00000000;

    #40;
    rd_add <= 10'b0000000000;
    #40;
    rd_add <= 10'b0000000010;
    #40;
    we <= 1;
    wr_add <= 10'b0000000010;
    d <= 8'b11010011;
    rd_add <= 10'b0000000011;
    #40;
    rd_add <= 10'b0000000010;
    #40;
    $finish;
end

initial begin 
    $monitor("clk = %b, we = %b, wr_add = %10b, rd_add = %10b, d = %8b, q = %8b", clk, we, wr_add, rd_add, d, q);
end

endmodule

ram/test.vcd
$date
	Mon Jul 22 14:31:50 2024
$end
$version
	Icarus Verilog
$end
$timescale
	1ns
$end
$scope module DPRAM_tb $end
$var wire 8 ! q [7:0] $end
$var reg 1 " clk $end
$var reg 8 # d [7:0] $end
$var reg 10 $ rd_add [9:0] $end
$var reg 1 % we $end
$var reg 10 & wr_add [9:0] $end
$scope module circ1 $end
$var wire 1 " clk $end
$var wire 8 ' d [7:0] $end
$var wire 8 ( q [7:0] $end
$var wire 10 ) rd_add [9:0] $end
$var wire 1 % we $end
$var wire 10 * wr_add [9:0] $end
$var parameter 32 + addr_width $end
$var parameter 32 , data_width $end
$var reg 8 - data_reg [7:0] $end
$upscope $end
$upscope $end
$enddefinitions $end
$comment Show the parameter values. $end
$dumpall
b1000 ,
b1010 +
$end
#0
$dumpvars
bx -
bx *
bx )
bx (
bx '
bx &
0%
bx $
bx #
0"
bx !
$end
#10
1"
#20
0"
#30
1"
#40
b0 $
b0 )
0"
#50
b11101111 !
b11101111 (
b11101111 -
1"
#60
0"
#70
1"
#80
b10 $
b10 )
0"
#90
b11111111 !
b11111111 (
b11111111 -
1"
#100
0"
#110
1"
#120
b11 $
b11 )
b11010011 #
b11010011 '
b10 &
b10 *
1%
0"
#130
b11111110 !
b11111110 (
b11111110 -
1"
#140
0"
#150
1"
#160
b10 $
b10 )
0"
#170
b11010011 !
b11010011 (
b11010011 -
1"
