String_Matcher/string_datapath.v
module string_datapath(
    input wire [3:0] datapath_in1, datapath_in2,
    output wire datapath_out
);

assign datapath_out = datapath_in1 == datapath_in2 - 1;

endmodule

String_Matcher/string_controller.v
module string_controller(
    input wire clk, reset, start,
    input wire x_val,
    output reg y_val,
    output wire [3:0] datapath_in1, datapath_in2,
    input wire datapath_out  
);

reg [3:0] nstate, pstate;
reg [3:0] i_pstate, i_nstate;

parameter [3:0] A = 4'b0000,
                B = 4'b0001,
                C = 4'b0010,
            ERROR = 4'b0011;

//Memory Design 

always @(posedge clk, posedge reset) begin : PSR

    if(reset)
        begin
            pstate <= A;
            i_pstate <= 4'b0000;
        end
    else
        begin
            pstate <= nstate;
            i_pstate <= i_nstate;
        end
end

//Next state Logic design

always @(*) begin : NSOL
    
    if(pstate == A)
        $monitor("pstate = A -> clk = %b, reset = %b, start = %b, x_val = %b, y_val = %b, i = %d\n", clk, reset, start, x_val, y_val, i_pstate);
    else if(pstate == B)
        $monitor("pstate = B -> clk = %b, reset = %b, start = %b, x_val = %b, y_val = %b, i = %d\n", clk, reset, start, x_val, y_val, i_pstate);
    else if(pstate == C)
        $monitor("pstate = C -> clk = %b, reset = %b, start = %b, x_val = %b, y_val = %b, i = %d\n", clk, reset, start, x_val, y_val, i_pstate);
    
    nstate = pstate;  

    begin : NSL 

        case(pstate)

            A : 
                begin
                    if(start)
                        begin
                            nstate = (x_val) ? B : A;
                        end
                end

            B : 
                begin
                            nstate = (x_val) ? ((datapath_out) ? C : B) : A;
                end

            C : 
                begin
                            nstate = (x_val) ? C : A;
                end

            default:        nstate = ERROR;
        
        endcase

    end

    begin : OL

        case(pstate)

            A : begin 
                    y_val = 1'b0;
                    i_nstate = 4'b0000;
                end

            B : begin 
                    y_val = 1'b0;
                    i_nstate = i_pstate + 1;
                end    

            C : begin 
                    y_val = 1'b1;
                    i_nstate = i_pstate + 1;
                end
            
            default : nstate = ERROR;

        endcase      
    end
end

assign datapath_in1 = i_pstate;
assign datapath_in2 = 4;


endmodule

String_Matcher/string_top.v
module string_top(
    input wire clk, reset, start,
    input wire a, b,
    output wire y_val
);

wire x_val;
wire [3:0] datapath_in1, datapath_in2;
wire datapath_out;

assign x_val = ~(a ^ b);

string_controller controller1(

    .clk(clk), 
    .reset(reset), 
    .start(start),
    .x_val(x_val),
    .y_val(y_val),
    .datapath_in1(datapath_in1), 
    .datapath_in2(datapath_in2),
    .datapath_out(datapath_out) 
);


string_datapath datapath1(
    .datapath_in1(datapath_in1), 
    .datapath_in2(datapath_in2),
    .datapath_out(datapath_out)
);

endmodule

String_Matcher/string_top_tb.sv
`timescale 1ns/1ps

module string_top_tb;

reg clk, reset, start;
reg a, b;
wire y_val;

string_top DUT(
    .clk(clk),
    .reset(reset),
    .start(start),
    .a(a),
    .b(b), 
    .y_val(y_val)
);

initial begin
    clk = 0;
    forever #5 clk = ~clk;
end

initial begin
    $dumpfile("test.vcd");
    $dumpvars(0, string_top_tb);

    clk <= 0;
    reset <= 0;
    start <= 0;
    a <= 0;
    b <= 0;

    @(negedge clk)
    reset <= 1;

    @(negedge clk)
    reset <= 0;
    start <= 1;
    a <= 1;
    b <= 1;

    repeat(10) @(negedge clk);

    $finish();

end

endmodule

String_Matcher/test.vcd
$date
	Fri Sep 20 00:24:31 2024
$end
$version
	Icarus Verilog
$end
$timescale
	1ps
$end
$scope module string_top_tb $end
$var wire 1 ! y_val $end
$var reg 1 " a $end
$var reg 1 # b $end
$var reg 1 $ clk $end
$var reg 1 % reset $end
$var reg 1 & start $end
$scope module DUT $end
$var wire 1 " a $end
$var wire 1 # b $end
$var wire 1 $ clk $end
$var wire 4 ' datapath_in2 [3:0] $end
$var wire 1 % reset $end
$var wire 1 & start $end
$var wire 1 ( x_val $end
$var wire 1 ! y_val $end
$var wire 1 ) datapath_out $end
$var wire 4 * datapath_in1 [3:0] $end
$scope module controller1 $end
$var wire 1 $ clk $end
$var wire 4 + datapath_in2 [3:0] $end
$var wire 1 % reset $end
$var wire 1 & start $end
$var wire 1 ( x_val $end
$var wire 1 ) datapath_out $end
$var wire 4 , datapath_in1 [3:0] $end
$var parameter 4 - A $end
$var parameter 4 . B $end
$var parameter 4 / C $end
$var parameter 4 0 ERROR $end
$var reg 4 1 i_nstate [3:0] $end
$var reg 4 2 i_pstate [3:0] $end
$var reg 4 3 nstate [3:0] $end
$var reg 4 4 pstate [3:0] $end
$var reg 1 ! y_val $end
$scope begin NSOL $end
$scope begin NSL $end
$upscope $end
$scope begin OL $end
$upscope $end
$upscope $end
$scope begin PSR $end
$upscope $end
$upscope $end
$scope module datapath1 $end
$var wire 4 5 datapath_in1 [3:0] $end
$var wire 4 6 datapath_in2 [3:0] $end
$var wire 1 ) datapath_out $end
$upscope $end
$upscope $end
$upscope $end
$enddefinitions $end
$comment Show the parameter values. $end
$dumpall
b11 0
b10 /
b1 .
b0 -
$end
#0
$dumpvars
b100 6
bx 5
bx 4
b11 3
bx 2
bx 1
bx ,
b100 +
bx *
x)
1(
b100 '
0&
0%
0$
0#
0"
x!
$end
#5000
b11 4
b11 3
1$
#10000
b0 1
0!
b0 3
0)
b0 *
b0 ,
b0 2
b0 5
b0 4
1%
0$
#15000
1$
#20000
b1 3
1#
1"
1&
0%
0$
#25000
b1 1
b1 4
b1 3
1$
#30000
0$
#35000
b10 1
b1 *
b1 ,
b1 2
b1 5
1$
#40000
0$
#45000
b11 1
b10 *
b10 ,
b10 2
b10 5
1$
#50000
0$
#55000
b100 1
b10 3
1)
b11 *
b11 ,
b11 2
b11 5
1$
#60000
b10 3
0$
#65000
b101 1
1!
0)
b100 *
b100 ,
b100 2
b100 5
b10 4
b10 3
1$
#70000
0$
#75000
b110 1
b101 *
b101 ,
b101 2
b101 5
1$
#80000
0$
#85000
b111 1
b110 *
b110 ,
b110 2
b110 5
1$
#90000
0$
#95000
b1000 1
b111 *
b111 ,
b111 2
b111 5
1$
#100000
0$
#105000
b1001 1
b1000 *
b1000 ,
b1000 2
b1000 5
1$
#110000
0$
#115000
b1010 1
b1001 *
b1001 ,
b1001 2
b1001 5
1$
