Temperature_Controller/temp_comp.v
module temp_comp(
    input wire [6:0] datapath_in1, datapath_in2, datapath_in3,
    output wire [3:0] datapath_out
);

assign datapath_out[0] = datapath_in1 < datapath_in2 - datapath_in3;
assign datapath_out[1] = datapath_in1 > datapath_in2 + datapath_in3;
assign datapath_out[2] = datapath_in1 > datapath_in2;
assign datapath_out[3] = datapath_in1 < datapath_in2;

endmodule

Temperature_Controller/temp_controller.v
module temp_controller(
    input wire clk, reset, start,
    input wire [6:0] troom, tref, dt,
    input wire [3:0] datapath_out,
    output reg h, c,
    output wire [6:0] datapath_in1, datapath_in2, datapath_in3
);

reg [3:0] pstate, nstate;

parameter [3:0] IDLE = 4'b0000,
                HOT =  4'b0001,
                COLD = 4'b0010,
                ERROR = 4'b0011;

//Memory Design 
always @(posedge clk, negedge reset) 
begin : PSR
    if(~reset)
        begin
            pstate <= IDLE;
        end
    else
        begin
            pstate <= nstate;
        end
end

//Next State Logic
always @(*) begin : NSOL

    if(pstate == IDLE)
        $monitor("pstate = IDLE -> clk = %b, reset = %b, start = %b, troom = %d, tref = %d, dt = %d, h = %b, c = %b\n", clk, reset, start, troom, tref, dt, h, c);
    
    else if(pstate == HOT)
        $monitor("pstate = HOT -> clk = %b, reset = %b, start = %b, troom = %d, tref = %d, dt = %d, h = %b, c = %b\n", clk, reset, start, troom, tref, dt, h, c);
 
    else if(pstate == COLD)
        $monitor("pstate = COLD -> clk = %b, reset = %b, start = %b, troom = %d, tref = %d, dt = %d, h = %b, c = %b\n", clk, reset, start, troom, tref, dt, h, c);

    nstate = pstate;


        begin : NSL

            case(pstate)

                IDLE :
                        begin
                            if(start)
                                begin
                                    nstate = (datapath_out[0]) ? HOT : 
                                        (datapath_out[1]) ? COLD :
                                        IDLE;
                                end
                        end
                
                HOT:    
                    begin
                
                        nstate = (datapath_out[2]) ? IDLE :
                                    HOT;
                    end

                COLD: 
                    begin
                        nstate = (datapath_out[3]) ? IDLE :
                                     COLD;
                    end

            default: nstate = ERROR; 

        endcase
        end

        begin : OL

            case(pstate)
            
                IDLE: 
                begin
                     h = 1'b0;
                      c = 1'b0;
                end      

                HOT: 
                begin
                h = 1'b1;
                    c = 1'b0;
                end
                
                COLD: 
                begin
                h = 1'b0;
                      c = 1'b1;
                end
            
            default : nstate = ERROR;

            endcase

        end

end

assign datapath_in1 = troom;
assign datapath_in2 = tref;
assign datapath_in3 = dt;

endmodule

Temperature_Controller/temp_top.v
module temp_top(
    input wire clk, reset, start,
    input wire [6:0] troom, tref, dt,
    output wire h, c 
    
);

wire [6:0] datapath_in1, datapath_in2, datapath_in3;
wire [3:0] datapath_out;

temp_controller temp1(

            .clk(clk),
            .reset(reset), 
            .start(start), 
            .troom(troom), 
            .tref(tref), 
            .dt(dt),
            .h(h),
            .c(c),
            .datapath_in1(datapath_in1),
            .datapath_in2(datapath_in2),
            .datapath_in3(datapath_in3),
            .datapath_out(datapath_out)
);

temp_comp comp1(
            .datapath_in1(datapath_in1), 
            .datapath_in2(datapath_in2), 
            .datapath_in3(datapath_in3),
            .datapath_out(datapath_out)
);


endmodule

Temperature_Controller/temp_top_tb.sv
`timescale 1ns/1ns

module temp_top_tb;

    reg clk, reset, start;
    reg [6:0] troom, tref, dt;
    wire h, c;

temp_top top1(
     .clk(clk),
     .reset(reset),
     .start(start),
     .troom(troom),
     .tref(tref),
     .dt(dt),
     .h(h),
     .c(c)
);

initial begin
    clk = 0;
    forever #5 clk=~clk;
end

initial begin

    $dumpfile("test10.vcd");
    $dumpvars(0, temp_top_tb);

   	clk <= 0;
	reset <= 0;
	start <= 0; 	
    troom <= 0;
    tref <= 0;
    dt <= 0;

	@(negedge clk);
	reset <= 0;

	@(negedge clk);
	reset <= 1;
	start <= 1;
    troom <= 50;
    tref <= 60;
    dt <= 1;
    #20;

    troom <= 61;
    #20;

    troom <= 80;
    #20;

    troom <= 59;
    #20;

	$finish();
end

endmodule

Temperature_Controller/test10.vcd
$date
	Thu Sep 19 17:14:12 2024
$end
$version
	Icarus Verilog
$end
$timescale
	1ns
$end
$scope module temp_top_tb $end
$var wire 1 ! h $end
$var wire 1 " c $end
$var reg 1 # clk $end
$var reg 7 $ dt [6:0] $end
$var reg 1 % reset $end
$var reg 1 & start $end
$var reg 7 ' tref [6:0] $end
$var reg 7 ( troom [6:0] $end
$scope module top1 $end
$var wire 1 # clk $end
$var wire 7 ) dt [6:0] $end
$var wire 1 % reset $end
$var wire 1 & start $end
$var wire 7 * tref [6:0] $end
$var wire 7 + troom [6:0] $end
$var wire 1 ! h $end
$var wire 4 , datapath_out [3:0] $end
$var wire 7 - datapath_in3 [6:0] $end
$var wire 7 . datapath_in2 [6:0] $end
$var wire 7 / datapath_in1 [6:0] $end
$var wire 1 " c $end
$scope module comp1 $end
$var wire 4 0 datapath_out [3:0] $end
$var wire 7 1 datapath_in3 [6:0] $end
$var wire 7 2 datapath_in2 [6:0] $end
$var wire 7 3 datapath_in1 [6:0] $end
$upscope $end
$scope module temp1 $end
$var wire 1 # clk $end
$var wire 7 4 datapath_in1 [6:0] $end
$var wire 7 5 datapath_in2 [6:0] $end
$var wire 7 6 datapath_in3 [6:0] $end
$var wire 4 7 datapath_out [3:0] $end
$var wire 7 8 dt [6:0] $end
$var wire 1 % reset $end
$var wire 1 & start $end
$var wire 7 9 tref [6:0] $end
$var wire 7 : troom [6:0] $end
$var parameter 4 ; COLD $end
$var parameter 4 < ERROR $end
$var parameter 4 = HOT $end
$var parameter 4 > IDLE $end
$var reg 1 " c $end
$var reg 1 ! h $end
$var reg 4 ? nstate [3:0] $end
$var reg 4 @ pstate [3:0] $end
$scope begin NSOL $end
$scope begin NSL $end
$upscope $end
$scope begin OL $end
$upscope $end
$upscope $end
$scope begin PSR $end
$upscope $end
$upscope $end
$upscope $end
$upscope $end
$enddefinitions $end
$comment Show the parameter values. $end
$dumpall
b0 >
b1 =
b11 <
b10 ;
$end
#0
$dumpvars
b0 @
b0 ?
b0 :
b0 9
b0 8
b0 7
b0 6
b0 5
b0 4
b0 3
b0 2
b0 1
b0 0
b0 /
b0 .
b0 -
b0 ,
b0 +
b0 *
b0 )
b0 (
b0 '
0&
0%
b0 $
0#
0"
0!
$end
#5
1#
#10
0#
#15
1#
#20
b1 ?
b1 -
b1 1
b1 6
b1 $
b1 )
b1 8
b111100 .
b111100 2
b111100 5
b111100 '
b111100 *
b111100 9
b1001 ,
b1001 0
b1001 7
b110010 /
b110010 3
b110010 4
b110010 (
b110010 +
b110010 :
1&
1%
0#
#25
1!
b1 @
b1 ?
1#
#30
0#
#35
1#
#40
b0 ?
b100 ,
b100 0
b100 7
b111101 /
b111101 3
b111101 4
b111101 (
b111101 +
b111101 :
0#
#45
0!
b0 @
b0 ?
1#
#50
0#
#55
1#
#60
b10 ?
b110 ,
b110 0
b110 7
b1010000 /
b1010000 3
b1010000 4
b1010000 (
b1010000 +
b1010000 :
0#
#65
1"
b10 @
b10 ?
1#
#70
0#
#75
1#
#80
b0 ?
b1000 ,
b1000 0
b1000 7
b111011 /
b111011 3
b111011 4
b111011 (
b111011 +
b111011 :
0#
#85
0"
b0 @
b0 ?
1#
