traffic light controller/comparator.v
module comparator(
    input wire [6:0] count,
    output wire count_eq30, count_eq90, count_eq100, count_g_100);


        assign count_eq30 = count == 30;
        assign count_eq90 = count == 90;
        assign count_eq100 = count == 100;
        assign count_g_100 = count >= 100;

endmodule

traffic light controller/counter.v
module counter(
            input wire clk, reset, clear,
            output reg [6:0] count);
     
                always @(posedge clk or negedge reset) begin
                        if (~reset)
                            count <= 7'b0000000;
                        
                        else 
                            count <= clear ? 7'b0000000 : count + 1'b1;
                end
endmodule

traffic light controller/traffic_light_controller.v
module traffic_light_controller (
                input wire clk, reset, start,
                
                input wire count_eq30, count_eq90, count_eq100, count_g_100,
                output reg [3:0] at_state,
                output reg [3:0] at_side,
                output reg clear, R, G ,Y);

                reg [3:0] pstate, nstate;
                

                    parameter [3:0] IDLE = 4'b0000, //state declaration
                                    R_1 = 4'b0001,
                                    Y_1 = 4'b0011,
                                    G_1 = 4'b0010,

                                    R_2 = 4'b0100,
                                    Y_2 = 4'b0110,
                                    G_2 = 4'b0101,

                                    R_3 = 4'b0111,
                                    Y_3 = 4'b1001,
                                    G_3 = 4'b1000,

                                    R_4 = 4'b1010,
                                    Y_4 = 4'b1100,
                                    G_4 = 4'b1011;


                           always @(*) begin : NSOL
                                begin : NSL
                                    case(pstate) 

                                            IDLE : nstate = start ? R_1 : IDLE;

                                            R_1 : nstate = count_eq30 ? G_1 : (count_g_100 ? R_2 : R_1); 

                                            G_1 : nstate = count_eq90 ? Y_1 : G_1;

                                            Y_1 : nstate = count_eq100 ? R_1 : Y_1;

                                            R_2 : nstate = count_eq30 ? G_2 : (count_g_100 ? R_3 : R_2);

                                            G_2 : nstate = count_eq90 ? Y_2 : G_2 ;

                                            Y_2 : nstate = count_eq100 ? R_2 : Y_2 ;

                                            R_3 : nstate = count_eq30 ? G_3 : (count_g_100 ? R_4 : R_3);

                                            G_3 : nstate = count_eq90 ? Y_3 : G_3 ;

                                            Y_3 : nstate = count_eq100 ? R_3 : Y_3 ;

                                            R_4 : nstate = count_eq30 ? G_4 : (count_g_100 ? R_1 : R_4);

                                            G_4 : nstate = count_eq90 ? Y_4 : G_4 ;

                                            Y_4 : nstate = count_eq100 ? R_4 : Y_4 ;

                                            default : nstate = 4'bx;

                                    endcase
                                end

                                
                                begin : OL 
                                    case(pstate)

                                            IDLE : begin
                                                clear = 1'b1;
                                                at_state = 4'b0000;
                                                at_side = 4'bx;
                                                R = 1'bx;
                                                G = 1'bx;
                                                Y = 1'bx;
                                            end

                                            R_1 : begin
                                                clear = count_g_100;
                                                at_state = 4'b0001;
                                                at_side =  4'b0001;
                                                R = 1'b1;
                                                G = 1'b0;
                                                Y = 1'b0;
                                            end

                                            Y_1 : begin
                                                clear = 1'b0;
                                                at_state = 4'b0011;
                                                at_side = 4'b0001; 
                                                R = 1'b0;
                                                G = 1'b0;
                                                Y = 1'b1;   
                                            end

                                            G_1 : begin
                                                clear = 1'b0;
                                                at_state = 4'b0010;
                                                at_side = 4'b0001; 
                                                R = 1'b0;
                                                G = 1'b1;
                                                Y = 1'b0;   
                                            end 
                                            
                                            R_2 : begin
                                                clear = count_g_100;
                                                at_state = 4'b0100;
                                                at_side = 4'b0010;
                                                R = 1'b1;
                                                G = 1'b0;
                                                Y = 1'b0;
                                            end

                                            Y_2 : begin
                                                clear = 1'b0;
                                                at_state = 4'b0110;
                                                at_side = 4'b0010;   
                                                R = 1'b0;
                                                G = 1'b0;
                                                Y = 1'b1; 
                                            end

                                            G_2 : begin
                                                clear = 1'b0;
                                                at_state = 4'b0101;
                                                at_side = 4'b0010; 
                                                R = 1'b0;
                                                G = 1'b1;
                                                Y = 1'b0;   
                                            end 

                                            R_3 : begin
                                                clear = count_g_100;
                                                at_state = 4'b0111;
                                                at_side = 4'b0100;
                                                R = 1'b1;
                                                G = 1'b0;
                                                Y = 1'b0;
                                            end

                                            Y_3 : begin
                                                clear = 1'b0;
                                                at_state = 4'b1001;
                                                at_side = 4'b0100;
                                                R = 1'b0;
                                                G = 1'b0;
                                                Y = 1'b1;     
                                            end

                                            G_3 : begin
                                                clear = 1'b0;
                                                at_state = 4'b1000;
                                                at_side = 4'b0100;  
                                                R = 1'b0;
                                                G = 1'b1;
                                                Y = 1'b0;  
                                            end

                                            R_4 : begin
                                                clear = count_g_100;
                                                at_state = 4'b1010;
                                                at_side = 4'b1000;
                                                R = 1'b1;
                                                G = 1'b0;
                                                Y = 1'b0;
                                            end

                                            Y_4 : begin
                                                clear = 1'b0;
                                                at_state = 4'b1100;
                                                at_side = 4'b1000;  
                                                R = 1'b0;
                                                G = 1'b0;
                                                Y = 1'b1;  
                                            end

                                            G_4 : begin
                                                clear = 1'b0;
                                                at_state = 4'b1011;
                                                at_side = 4'b1000;  
                                                R = 1'b0;
                                                G = 1'b1;
                                                Y = 1'b0;  
                                            end

                                            default : begin
                                                clear = 1'bx;
                                                at_state = 4'bx;
                                                at_side = 4'bx;
                                                R = 1'bx;
                                                G = 1'bx;
                                                Y = 1'bx;
                                            end
                                endcase
                            end

                            end

                        always @(posedge clk or negedge reset) begin : PSR
                                begin
                                        if(~reset) begin 
                                            pstate <= IDLE;
                                        end

                                        else begin
                                            pstate <= nstate;
                                        end
                                end
                        end

endmodule

traffic light controller/top.v
module top(
        input wire clk, reset, start,
        output wire [3:0] at_side,
        output wire [3:0] at_state,
        output wire R, G ,Y);

        wire clear, count_eq30, count_eq90, count_eq100, count_g_100;
        wire [6:0] count;                               

            traffic_light_controller tfc1 (
                                            .clk(clk),
                                            .reset(reset),
                                            .start(start),
                                            .count_eq30(count_eq30),
                                            .count_eq90(count_eq90),
                                            .count_eq100(count_eq100),
                                            .count_g_100(count_g_100),
                                            .at_state(at_state),
                                            .clear(clear),
                                            .at_side(at_side),
                                            .R(R),
                                            .G(G),
                                            .Y(Y));     

                          counter count1 (
                                            .clk(clk),
                                            .reset(reset),
                                            .clear(clear),
                                            .count(count)); 

                        comparator comp1 (
                                            .count(count),
                                            .count_eq30(count_eq30),
                                            .count_eq90(count_eq90),
                                            .count_eq100(count_eq100),
                                            .count_g_100(count_g_100));

endmodule

traffic light controller/top_tb.v
`timescale 1ns/1ns
module top_tb;
        
        reg clk, reset, start;
        wire [3:0] at_side;
        wire [3:0] at_state;
        wire R, G ,Y;




        top top1(
                    .clk(clk),
                    .reset(reset),
                    .start(start),
                    .at_side(at_side),
                    .at_state(at_state),
                    .R(R),
                    .Y(Y),
                    .G(G));

            always begin
                clk = ~clk;
                #5;
            end

            initial begin 
                $dumpfile("test.vcd");
                $dumpvars(0, top_tb);

                    clk <= 0;
                    reset <= 0;
                    start <= 0;
                    //side <= 4'b0001;
                    
                    #20; start <= 1;

                    #20; reset <= 1;

//                    #20; side <= 4'bx;

                    repeat(200) #20;

                    $finish();
            end

endmodule

traffic light controller/test.vcd
$date
	Mon Jul 22 14:02:01 2024
$end
$version
	Icarus Verilog
$end
$timescale
	1ns
$end
$scope module top_tb $end
$var wire 4 ! at_state [3:0] $end
$var wire 4 " at_side [3:0] $end
$var wire 1 # Y $end
$var wire 1 $ R $end
$var wire 1 % G $end
$var reg 1 & clk $end
$var reg 1 ' reset $end
$var reg 1 ( start $end
$scope module top1 $end
$var wire 1 & clk $end
$var wire 1 ' reset $end
$var wire 1 ( start $end
$var wire 1 ) count_g_100 $end
$var wire 1 * count_eq90 $end
$var wire 1 + count_eq30 $end
$var wire 1 , count_eq100 $end
$var wire 7 - count [6:0] $end
$var wire 1 . clear $end
$var wire 4 / at_state [3:0] $end
$var wire 4 0 at_side [3:0] $end
$var wire 1 # Y $end
$var wire 1 $ R $end
$var wire 1 % G $end
$scope module comp1 $end
$var wire 1 ) count_g_100 $end
$var wire 1 * count_eq90 $end
$var wire 1 + count_eq30 $end
$var wire 1 , count_eq100 $end
$var wire 7 1 count [6:0] $end
$upscope $end
$scope module count1 $end
$var wire 1 & clk $end
$var wire 1 ' reset $end
$var wire 1 . clear $end
$var reg 7 2 count [6:0] $end
$upscope $end
$scope module tfc1 $end
$var wire 1 & clk $end
$var wire 1 , count_eq100 $end
$var wire 1 + count_eq30 $end
$var wire 1 * count_eq90 $end
$var wire 1 ) count_g_100 $end
$var wire 1 ' reset $end
$var wire 1 ( start $end
$var parameter 4 3 G_1 $end
$var parameter 4 4 G_2 $end
$var parameter 4 5 G_3 $end
$var parameter 4 6 G_4 $end
$var parameter 4 7 IDLE $end
$var parameter 4 8 R_1 $end
$var parameter 4 9 R_2 $end
$var parameter 4 : R_3 $end
$var parameter 4 ; R_4 $end
$var parameter 4 < Y_1 $end
$var parameter 4 = Y_2 $end
$var parameter 4 > Y_3 $end
$var parameter 4 ? Y_4 $end
$var reg 1 % G $end
$var reg 1 $ R $end
$var reg 1 # Y $end
$var reg 4 @ at_side [3:0] $end
$var reg 4 A at_state [3:0] $end
$var reg 1 . clear $end
$var reg 4 B nstate [3:0] $end
$var reg 4 C pstate [3:0] $end
$scope begin NSOL $end
$scope begin NSL $end
$upscope $end
$scope begin OL $end
$upscope $end
$upscope $end
$scope begin PSR $end
$upscope $end
$upscope $end
$upscope $end
$upscope $end
$enddefinitions $end
$comment Show the parameter values. $end
$dumpall
b1100 ?
b1001 >
b110 =
b11 <
b1010 ;
b111 :
b100 9
b1 8
b0 7
b1011 6
b1000 5
b101 4
b10 3
$end
#0
$dumpvars
b0 C
b0 B
b0 A
bx @
b0 2
b0 1
bx 0
b0 /
1.
b0 -
0,
0+
0*
0)
0(
0'
0&
x%
x$
x#
bx "
b0 !
$end
#5
1&
#10
0&
#15
1&
#20
b1 B
1(
0&
#25
1&
#30
0&
#35
1&
#40
1'
0&
#45
0#
0%
1$
b1 "
b1 0
b1 @
b1 !
b1 /
b1 A
0.
b1 C
1&
#50
0&
#55
b1 -
b1 1
b1 2
1&
#60
0&
#65
b10 -
b10 1
b10 2
1&
#70
0&
#75
b11 -
b11 1
b11 2
1&
#80
0&
#85
b100 -
b100 1
b100 2
1&
#90
0&
#95
b101 -
b101 1
b101 2
1&
#100
0&
#105
b110 -
b110 1
b110 2
1&
#110
0&
#115
b111 -
b111 1
b111 2
1&
#120
0&
#125
b1000 -
b1000 1
b1000 2
1&
#130
0&
#135
b1001 -
b1001 1
b1001 2
1&
#140
0&
#145
b1010 -
b1010 1
b1010 2
1&
#150
0&
#155
b1011 -
b1011 1
b1011 2
1&
#160
0&
#165
b1100 -
b1100 1
b1100 2
1&
#170
0&
#175
b1101 -
b1101 1
b1101 2
1&
#180
0&
#185
b1110 -
b1110 1
b1110 2
1&
#190
0&
#195
b1111 -
b1111 1
b1111 2
1&
#200
0&
#205
b10000 -
b10000 1
b10000 2
1&
#210
0&
#215
b10001 -
b10001 1
b10001 2
1&
#220
0&
#225
b10010 -
b10010 1
b10010 2
1&
#230
0&
#235
b10011 -
b10011 1
b10011 2
1&
#240
0&
#245
b10100 -
b10100 1
b10100 2
1&
#250
0&
#255
b10101 -
b10101 1
b10101 2
1&
#260
0&
#265
b10110 -
b10110 1
b10110 2
1&
#270
0&
#275
b10111 -
b10111 1
b10111 2
1&
#280
0&
#285
b11000 -
b11000 1
b11000 2
1&
#290
0&
#295
b11001 -
b11001 1
b11001 2
1&
#300
0&
#305
b11010 -
b11010 1
b11010 2
1&
#310
0&
#315
b11011 -
b11011 1
b11011 2
1&
#320
0&
#325
b11100 -
b11100 1
b11100 2
1&
#330
0&
#335
b11101 -
b11101 1
b11101 2
1&
#340
0&
#345
b10 B
1+
b11110 -
b11110 1
b11110 2
1&
#350
0&
#355
1%
0$
b10 !
b10 /
b10 A
b10 C
0+
b11111 -
b11111 1
b11111 2
1&
#360
0&
#365
b100000 -
b100000 1
b100000 2
1&
#370
0&
#375
b100001 -
b100001 1
b100001 2
1&
#380
0&
#385
b100010 -
b100010 1
b100010 2
1&
#390
0&
#395
b100011 -
b100011 1
b100011 2
1&
#400
0&
#405
b100100 -
b100100 1
b100100 2
1&
#410
0&
#415
b100101 -
b100101 1
b100101 2
1&
#420
0&
#425
b100110 -
b100110 1
b100110 2
1&
#430
0&
#435
b100111 -
b100111 1
b100111 2
1&
#440
0&
#445
b101000 -
b101000 1
b101000 2
1&
#450
0&
#455
b101001 -
b101001 1
b101001 2
1&
#460
0&
#465
b101010 -
b101010 1
b101010 2
1&
#470
0&
#475
b101011 -
b101011 1
b101011 2
1&
#480
0&
#485
b101100 -
b101100 1
b101100 2
1&
#490
0&
#495
b101101 -
b101101 1
b101101 2
1&
#500
0&
#505
b101110 -
b101110 1
b101110 2
1&
#510
0&
#515
b101111 -
b101111 1
b101111 2
1&
#520
0&
#525
b110000 -
b110000 1
b110000 2
1&
#530
0&
#535
b110001 -
b110001 1
b110001 2
1&
#540
0&
#545
b110010 -
b110010 1
b110010 2
1&
#550
0&
#555
b110011 -
b110011 1
b110011 2
1&
#560
0&
#565
b110100 -
b110100 1
b110100 2
1&
#570
0&
#575
b110101 -
b110101 1
b110101 2
1&
#580
0&
#585
b110110 -
b110110 1
b110110 2
1&
#590
0&
#595
b110111 -
b110111 1
b110111 2
1&
#600
0&
#605
b111000 -
b111000 1
b111000 2
1&
#610
0&
#615
b111001 -
b111001 1
b111001 2
1&
#620
0&
#625
b111010 -
b111010 1
b111010 2
1&
#630
0&
#635
b111011 -
b111011 1
b111011 2
1&
#640
0&
#645
b111100 -
b111100 1
b111100 2
1&
#650
0&
#655
b111101 -
b111101 1
b111101 2
1&
#660
0&
#665
b111110 -
b111110 1
b111110 2
1&
#670
0&
#675
b111111 -
b111111 1
b111111 2
1&
#680
0&
#685
b1000000 -
b1000000 1
b1000000 2
1&
#690
0&
#695
b1000001 -
b1000001 1
b1000001 2
1&
#700
0&
#705
b1000010 -
b1000010 1
b1000010 2
1&
#710
0&
#715
b1000011 -
b1000011 1
b1000011 2
1&
#720
0&
#725
b1000100 -
b1000100 1
b1000100 2
1&
#730
0&
#735
b1000101 -
b1000101 1
b1000101 2
1&
#740
0&
#745
b1000110 -
b1000110 1
b1000110 2
1&
#750
0&
#755
b1000111 -
b1000111 1
b1000111 2
1&
#760
0&
#765
b1001000 -
b1001000 1
b1001000 2
1&
#770
0&
#775
b1001001 -
b1001001 1
b1001001 2
1&
#780
0&
#785
b1001010 -
b1001010 1
b1001010 2
1&
#790
0&
#795
b1001011 -
b1001011 1
b1001011 2
1&
#800
0&
#805
b1001100 -
b1001100 1
b1001100 2
1&
#810
0&
#815
b1001101 -
b1001101 1
b1001101 2
1&
#820
0&
#825
b1001110 -
b1001110 1
b1001110 2
1&
#830
0&
#835
b1001111 -
b1001111 1
b1001111 2
1&
#840
0&
#845
b1010000 -
b1010000 1
b1010000 2
1&
#850
0&
#855
b1010001 -
b1010001 1
b1010001 2
1&
#860
0&
#865
b1010010 -
b1010010 1
b1010010 2
1&
#870
0&
#875
b1010011 -
b1010011 1
b1010011 2
1&
#880
0&
#885
b1010100 -
b1010100 1
b1010100 2
1&
#890
0&
#895
b1010101 -
b1010101 1
b1010101 2
1&
#900
0&
#905
b1010110 -
b1010110 1
b1010110 2
1&
#910
0&
#915
b1010111 -
b1010111 1
b1010111 2
1&
#920
0&
#925
b1011000 -
b1011000 1
b1011000 2
1&
#930
0&
#935
b1011001 -
b1011001 1
b1011001 2
1&
#940
0&
#945
b11 B
1*
b1011010 -
b1011010 1
b1011010 2
1&
#950
0&
#955
1#
0%
b11 !
b11 /
b11 A
b11 C
0*
b1011011 -
b1011011 1
b1011011 2
1&
#960
0&
#965
b1011100 -
b1011100 1
b1011100 2
1&
#970
0&
#975
b1011101 -
b1011101 1
b1011101 2
1&
#980
0&
#985
b1011110 -
b1011110 1
b1011110 2
1&
#990
0&
#995
b1011111 -
b1011111 1
b1011111 2
1&
#1000
0&
#1005
b1100000 -
b1100000 1
b1100000 2
1&
#1010
0&
#1015
b1100001 -
b1100001 1
b1100001 2
1&
#1020
0&
#1025
b1100010 -
b1100010 1
b1100010 2
1&
#1030
0&
#1035
b1100011 -
b1100011 1
b1100011 2
1&
#1040
0&
#1045
b1 B
1)
1,
b1100100 -
b1100100 1
b1100100 2
1&
#1050
0&
#1055
0#
1$
b1 !
b1 /
b1 A
1.
b100 B
b1 C
0,
b1100101 -
b1100101 1
b1100101 2
1&
#1060
0&
#1065
b10 "
b10 0
b10 @
b100 !
b100 /
b100 A
0.
b100 C
0)
b0 -
b0 1
b0 2
1&
#1070
0&
#1075
b1 -
b1 1
b1 2
1&
#1080
0&
#1085
b10 -
b10 1
b10 2
1&
#1090
0&
#1095
b11 -
b11 1
b11 2
1&
#1100
0&
#1105
b100 -
b100 1
b100 2
1&
#1110
0&
#1115
b101 -
b101 1
b101 2
1&
#1120
0&
#1125
b110 -
b110 1
b110 2
1&
#1130
0&
#1135
b111 -
b111 1
b111 2
1&
#1140
0&
#1145
b1000 -
b1000 1
b1000 2
1&
#1150
0&
#1155
b1001 -
b1001 1
b1001 2
1&
#1160
0&
#1165
b1010 -
b1010 1
b1010 2
1&
#1170
0&
#1175
b1011 -
b1011 1
b1011 2
1&
#1180
0&
#1185
b1100 -
b1100 1
b1100 2
1&
#1190
0&
#1195
b1101 -
b1101 1
b1101 2
1&
#1200
0&
#1205
b1110 -
b1110 1
b1110 2
1&
#1210
0&
#1215
b1111 -
b1111 1
b1111 2
1&
#1220
0&
#1225
b10000 -
b10000 1
b10000 2
1&
#1230
0&
#1235
b10001 -
b10001 1
b10001 2
1&
#1240
0&
#1245
b10010 -
b10010 1
b10010 2
1&
#1250
0&
#1255
b10011 -
b10011 1
b10011 2
1&
#1260
0&
#1265
b10100 -
b10100 1
b10100 2
1&
#1270
0&
#1275
b10101 -
b10101 1
b10101 2
1&
#1280
0&
#1285
b10110 -
b10110 1
b10110 2
1&
#1290
0&
#1295
b10111 -
b10111 1
b10111 2
1&
#1300
0&
#1305
b11000 -
b11000 1
b11000 2
1&
#1310
0&
#1315
b11001 -
b11001 1
b11001 2
1&
#1320
0&
#1325
b11010 -
b11010 1
b11010 2
1&
#1330
0&
#1335
b11011 -
b11011 1
b11011 2
1&
#1340
0&
#1345
b11100 -
b11100 1
b11100 2
1&
#1350
0&
#1355
b11101 -
b11101 1
b11101 2
1&
#1360
0&
#1365
b101 B
1+
b11110 -
b11110 1
b11110 2
1&
#1370
0&
#1375
1%
0$
b101 !
b101 /
b101 A
b101 C
0+
b11111 -
b11111 1
b11111 2
1&
#1380
0&
#1385
b100000 -
b100000 1
b100000 2
1&
#1390
0&
#1395
b100001 -
b100001 1
b100001 2
1&
#1400
0&
#1405
b100010 -
b100010 1
b100010 2
1&
#1410
0&
#1415
b100011 -
b100011 1
b100011 2
1&
#1420
0&
#1425
b100100 -
b100100 1
b100100 2
1&
#1430
0&
#1435
b100101 -
b100101 1
b100101 2
1&
#1440
0&
#1445
b100110 -
b100110 1
b100110 2
1&
#1450
0&
#1455
b100111 -
b100111 1
b100111 2
1&
#1460
0&
#1465
b101000 -
b101000 1
b101000 2
1&
#1470
0&
#1475
b101001 -
b101001 1
b101001 2
1&
#1480
0&
#1485
b101010 -
b101010 1
b101010 2
1&
#1490
0&
#1495
b101011 -
b101011 1
b101011 2
1&
#1500
0&
#1505
b101100 -
b101100 1
b101100 2
1&
#1510
0&
#1515
b101101 -
b101101 1
b101101 2
1&
#1520
0&
#1525
b101110 -
b101110 1
b101110 2
1&
#1530
0&
#1535
b101111 -
b101111 1
b101111 2
1&
#1540
0&
#1545
b110000 -
b110000 1
b110000 2
1&
#1550
0&
#1555
b110001 -
b110001 1
b110001 2
1&
#1560
0&
#1565
b110010 -
b110010 1
b110010 2
1&
#1570
0&
#1575
b110011 -
b110011 1
b110011 2
1&
#1580
0&
#1585
b110100 -
b110100 1
b110100 2
1&
#1590
0&
#1595
b110101 -
b110101 1
b110101 2
1&
#1600
0&
#1605
b110110 -
b110110 1
b110110 2
1&
#1610
0&
#1615
b110111 -
b110111 1
b110111 2
1&
#1620
0&
#1625
b111000 -
b111000 1
b111000 2
1&
#1630
0&
#1635
b111001 -
b111001 1
b111001 2
1&
#1640
0&
#1645
b111010 -
b111010 1
b111010 2
1&
#1650
0&
#1655
b111011 -
b111011 1
b111011 2
1&
#1660
0&
#1665
b111100 -
b111100 1
b111100 2
1&
#1670
0&
#1675
b111101 -
b111101 1
b111101 2
1&
#1680
0&
#1685
b111110 -
b111110 1
b111110 2
1&
#1690
0&
#1695
b111111 -
b111111 1
b111111 2
1&
#1700
0&
#1705
b1000000 -
b1000000 1
b1000000 2
1&
#1710
0&
#1715
b1000001 -
b1000001 1
b1000001 2
1&
#1720
0&
#1725
b1000010 -
b1000010 1
b1000010 2
1&
#1730
0&
#1735
b1000011 -
b1000011 1
b1000011 2
1&
#1740
0&
#1745
b1000100 -
b1000100 1
b1000100 2
1&
#1750
0&
#1755
b1000101 -
b1000101 1
b1000101 2
1&
#1760
0&
#1765
b1000110 -
b1000110 1
b1000110 2
1&
#1770
0&
#1775
b1000111 -
b1000111 1
b1000111 2
1&
#1780
0&
#1785
b1001000 -
b1001000 1
b1001000 2
1&
#1790
0&
#1795
b1001001 -
b1001001 1
b1001001 2
1&
#1800
0&
#1805
b1001010 -
b1001010 1
b1001010 2
1&
#1810
0&
#1815
b1001011 -
b1001011 1
b1001011 2
1&
#1820
0&
#1825
b1001100 -
b1001100 1
b1001100 2
1&
#1830
0&
#1835
b1001101 -
b1001101 1
b1001101 2
1&
#1840
0&
#1845
b1001110 -
b1001110 1
b1001110 2
1&
#1850
0&
#1855
b1001111 -
b1001111 1
b1001111 2
1&
#1860
0&
#1865
b1010000 -
b1010000 1
b1010000 2
1&
#1870
0&
#1875
b1010001 -
b1010001 1
b1010001 2
1&
#1880
0&
#1885
b1010010 -
b1010010 1
b1010010 2
1&
#1890
0&
#1895
b1010011 -
b1010011 1
b1010011 2
1&
#1900
0&
#1905
b1010100 -
b1010100 1
b1010100 2
1&
#1910
0&
#1915
b1010101 -
b1010101 1
b1010101 2
1&
#1920
0&
#1925
b1010110 -
b1010110 1
b1010110 2
1&
#1930
0&
#1935
b1010111 -
b1010111 1
b1010111 2
1&
#1940
0&
#1945
b1011000 -
b1011000 1
b1011000 2
1&
#1950
0&
#1955
b1011001 -
b1011001 1
b1011001 2
1&
#1960
0&
#1965
b110 B
1*
b1011010 -
b1011010 1
b1011010 2
1&
#1970
0&
#1975
1#
0%
b110 !
b110 /
b110 A
b110 C
0*
b1011011 -
b1011011 1
b1011011 2
1&
#1980
0&
#1985
b1011100 -
b1011100 1
b1011100 2
1&
#1990
0&
#1995
b1011101 -
b1011101 1
b1011101 2
1&
#2000
0&
#2005
b1011110 -
b1011110 1
b1011110 2
1&
#2010
0&
#2015
b1011111 -
b1011111 1
b1011111 2
1&
#2020
0&
#2025
b1100000 -
b1100000 1
b1100000 2
1&
#2030
0&
#2035
b1100001 -
b1100001 1
b1100001 2
1&
#2040
0&
#2045
b1100010 -
b1100010 1
b1100010 2
1&
#2050
0&
#2055
b1100011 -
b1100011 1
b1100011 2
1&
#2060
0&
#2065
b100 B
1)
1,
b1100100 -
b1100100 1
b1100100 2
1&
#2070
0&
#2075
0#
1$
b100 !
b100 /
b100 A
1.
b111 B
b100 C
0,
b1100101 -
b1100101 1
b1100101 2
1&
#2080
0&
#2085
b100 "
b100 0
b100 @
b111 !
b111 /
b111 A
0.
b111 C
0)
b0 -
b0 1
b0 2
1&
#2090
0&
#2095
b1 -
b1 1
b1 2
1&
#2100
0&
#2105
b10 -
b10 1
b10 2
1&
#2110
0&
#2115
b11 -
b11 1
b11 2
1&
#2120
0&
#2125
b100 -
b100 1
b100 2
1&
#2130
0&
#2135
b101 -
b101 1
b101 2
1&
#2140
0&
#2145
b110 -
b110 1
b110 2
1&
#2150
0&
#2155
b111 -
b111 1
b111 2
1&
#2160
0&
#2165
b1000 -
b1000 1
b1000 2
1&
#2170
0&
#2175
b1001 -
b1001 1
b1001 2
1&
#2180
0&
#2185
b1010 -
b1010 1
b1010 2
1&
#2190
0&
#2195
b1011 -
b1011 1
b1011 2
1&
#2200
0&
#2205
b1100 -
b1100 1
b1100 2
1&
#2210
0&
#2215
b1101 -
b1101 1
b1101 2
1&
#2220
0&
#2225
b1110 -
b1110 1
b1110 2
1&
#2230
0&
#2235
b1111 -
b1111 1
b1111 2
1&
#2240
0&
#2245
b10000 -
b10000 1
b10000 2
1&
#2250
0&
#2255
b10001 -
b10001 1
b10001 2
1&
#2260
0&
#2265
b10010 -
b10010 1
b10010 2
1&
#2270
0&
#2275
b10011 -
b10011 1
b10011 2
1&
#2280
0&
#2285
b10100 -
b10100 1
b10100 2
1&
#2290
0&
#2295
b10101 -
b10101 1
b10101 2
1&
#2300
0&
#2305
b10110 -
b10110 1
b10110 2
1&
#2310
0&
#2315
b10111 -
b10111 1
b10111 2
1&
#2320
0&
#2325
b11000 -
b11000 1
b11000 2
1&
#2330
0&
#2335
b11001 -
b11001 1
b11001 2
1&
#2340
0&
#2345
b11010 -
b11010 1
b11010 2
1&
#2350
0&
#2355
b11011 -
b11011 1
b11011 2
1&
#2360
0&
#2365
b11100 -
b11100 1
b11100 2
1&
#2370
0&
#2375
b11101 -
b11101 1
b11101 2
1&
#2380
0&
#2385
b1000 B
1+
b11110 -
b11110 1
b11110 2
1&
#2390
0&
#2395
1%
0$
b1000 !
b1000 /
b1000 A
b1000 C
0+
b11111 -
b11111 1
b11111 2
1&
#2400
0&
#2405
b100000 -
b100000 1
b100000 2
1&
#2410
0&
#2415
b100001 -
b100001 1
b100001 2
1&
#2420
0&
#2425
b100010 -
b100010 1
b100010 2
1&
#2430
0&
#2435
b100011 -
b100011 1
b100011 2
1&
#2440
0&
#2445
b100100 -
b100100 1
b100100 2
1&
#2450
0&
#2455
b100101 -
b100101 1
b100101 2
1&
#2460
0&
#2465
b100110 -
b100110 1
b100110 2
1&
#2470
0&
#2475
b100111 -
b100111 1
b100111 2
1&
#2480
0&
#2485
b101000 -
b101000 1
b101000 2
1&
#2490
0&
#2495
b101001 -
b101001 1
b101001 2
1&
#2500
0&
#2505
b101010 -
b101010 1
b101010 2
1&
#2510
0&
#2515
b101011 -
b101011 1
b101011 2
1&
#2520
0&
#2525
b101100 -
b101100 1
b101100 2
1&
#2530
0&
#2535
b101101 -
b101101 1
b101101 2
1&
#2540
0&
#2545
b101110 -
b101110 1
b101110 2
1&
#2550
0&
#2555
b101111 -
b101111 1
b101111 2
1&
#2560
0&
#2565
b110000 -
b110000 1
b110000 2
1&
#2570
0&
#2575
b110001 -
b110001 1
b110001 2
1&
#2580
0&
#2585
b110010 -
b110010 1
b110010 2
1&
#2590
0&
#2595
b110011 -
b110011 1
b110011 2
1&
#2600
0&
#2605
b110100 -
b110100 1
b110100 2
1&
#2610
0&
#2615
b110101 -
b110101 1
b110101 2
1&
#2620
0&
#2625
b110110 -
b110110 1
b110110 2
1&
#2630
0&
#2635
b110111 -
b110111 1
b110111 2
1&
#2640
0&
#2645
b111000 -
b111000 1
b111000 2
1&
#2650
0&
#2655
b111001 -
b111001 1
b111001 2
1&
#2660
0&
#2665
b111010 -
b111010 1
b111010 2
1&
#2670
0&
#2675
b111011 -
b111011 1
b111011 2
1&
#2680
0&
#2685
b111100 -
b111100 1
b111100 2
1&
#2690
0&
#2695
b111101 -
b111101 1
b111101 2
1&
#2700
0&
#2705
b111110 -
b111110 1
b111110 2
1&
#2710
0&
#2715
b111111 -
b111111 1
b111111 2
1&
#2720
0&
#2725
b1000000 -
b1000000 1
b1000000 2
1&
#2730
0&
#2735
b1000001 -
b1000001 1
b1000001 2
1&
#2740
0&
#2745
b1000010 -
b1000010 1
b1000010 2
1&
#2750
0&
#2755
b1000011 -
b1000011 1
b1000011 2
1&
#2760
0&
#2765
b1000100 -
b1000100 1
b1000100 2
1&
#2770
0&
#2775
b1000101 -
b1000101 1
b1000101 2
1&
#2780
0&
#2785
b1000110 -
b1000110 1
b1000110 2
1&
#2790
0&
#2795
b1000111 -
b1000111 1
b1000111 2
1&
#2800
0&
#2805
b1001000 -
b1001000 1
b1001000 2
1&
#2810
0&
#2815
b1001001 -
b1001001 1
b1001001 2
1&
#2820
0&
#2825
b1001010 -
b1001010 1
b1001010 2
1&
#2830
0&
#2835
b1001011 -
b1001011 1
b1001011 2
1&
#2840
0&
#2845
b1001100 -
b1001100 1
b1001100 2
1&
#2850
0&
#2855
b1001101 -
b1001101 1
b1001101 2
1&
#2860
0&
#2865
b1001110 -
b1001110 1
b1001110 2
1&
#2870
0&
#2875
b1001111 -
b1001111 1
b1001111 2
1&
#2880
0&
#2885
b1010000 -
b1010000 1
b1010000 2
1&
#2890
0&
#2895
b1010001 -
b1010001 1
b1010001 2
1&
#2900
0&
#2905
b1010010 -
b1010010 1
b1010010 2
1&
#2910
0&
#2915
b1010011 -
b1010011 1
b1010011 2
1&
#2920
0&
#2925
b1010100 -
b1010100 1
b1010100 2
1&
#2930
0&
#2935
b1010101 -
b1010101 1
b1010101 2
1&
#2940
0&
#2945
b1010110 -
b1010110 1
b1010110 2
1&
#2950
0&
#2955
b1010111 -
b1010111 1
b1010111 2
1&
#2960
0&
#2965
b1011000 -
b1011000 1
b1011000 2
1&
#2970
0&
#2975
b1011001 -
b1011001 1
b1011001 2
1&
#2980
0&
#2985
b1001 B
1*
b1011010 -
b1011010 1
b1011010 2
1&
#2990
0&
#2995
1#
0%
b1001 !
b1001 /
b1001 A
b1001 C
0*
b1011011 -
b1011011 1
b1011011 2
1&
#3000
0&
#3005
b1011100 -
b1011100 1
b1011100 2
1&
#3010
0&
#3015
b1011101 -
b1011101 1
b1011101 2
1&
#3020
0&
#3025
b1011110 -
b1011110 1
b1011110 2
1&
#3030
0&
#3035
b1011111 -
b1011111 1
b1011111 2
1&
#3040
0&
#3045
b1100000 -
b1100000 1
b1100000 2
1&
#3050
0&
