counter/gray counter/graycounter.v
module graycounter
#(
    parameter data_width = 4
)
(
    input wire clk,
    input wire load_en,
    input wire reset,
    input wire [data_width-1:0] d,
    output reg [data_width-1:0] q
);

reg [data_width-1:0] count;
reg q2,q1,q0;

always @(posedge clk, posedge reset)
 begin
    if(reset)
     begin
     q <= 4'b0000;
     count <= 4'b0000;
     {q2,q1,q0} <= 3'b000;
     end
    else if(load_en)
     begin
        q <= d;
        count <=d;
        {q2,q1,q0} <= {d[2],d[1],d[0]};
     end
    else
     begin
        count <= count + 4'b0001;
        q2 <= count[3] ^ count[2];
        q1 <= count[2] ^ count[1];
        q0 <= count[1] ^ count[0];
        q <= {count[3], q2, q1, q0};
     end
end
endmodule

counter/gray counter/graycounter_tb.v
`timescale 1ns/1ns

module graycounter_tb;
 reg clk;
 reg load_en;
 reg reset;
 reg [3:0] d;
 wire [3:0] q;

graycounter circ(clk, load_en, reset, d, q);

always begin
    clk = ~clk;
    #10;
end

initial begin
    $dumpfile("test.vcd");
    $dumpvars(0, graycounter_tb);

    clk <=0;
    reset <= 1;
    load_en <= 0;

    #20;
    reset <= 0;
    #20;
    load_en <= 1;
    d <= 4'b0011;
    #20;
    
    load_en <= 0;
    #20;
    
    #20;
    #20;
    #20;
    reset <= 1;
    #20;
    #20;
    $finish;
end

initial begin
    $monitor("time = %0t, clk = %b, load_en = %b, reset = %b, d = %b, q = %b",$time, clk, load_en, reset, d, q);
end
endmodule

counter/gray counter/test.vcd
$date
	Fri Jul 12 01:01:37 2024
$end
$version
	Icarus Verilog
$end
$timescale
	1ns
$end
$scope module graycounter_tb $end
$var wire 4 ! q [3:0] $end
$var reg 1 " clk $end
$var reg 4 # d [3:0] $end
$var reg 1 $ load_en $end
$var reg 1 % reset $end
$scope module circ $end
$var wire 1 " clk $end
$var wire 4 & d [3:0] $end
$var wire 1 $ load_en $end
$var wire 1 % reset $end
$var parameter 32 ' data_width $end
$var reg 4 ( count [3:0] $end
$var reg 4 ) q [3:0] $end
$var reg 1 * q0 $end
$var reg 1 + q1 $end
$var reg 1 , q2 $end
$upscope $end
$upscope $end
$enddefinitions $end
$comment Show the parameter values. $end
$dumpall
b100 '
$end
#0
$dumpvars
0,
0+
0*
b0 )
b0 (
bx &
1%
0$
bx #
0"
b0 !
$end
#10
1"
#20
0%
0"
#30
b1 (
1"
#40
b11 #
b11 &
1$
0"
#50
1+
1*
b11 (
b11 !
b11 )
1"
#60
0$
0"
#70
0*
b100 (
1"
#80
0"
#90
b10 !
b10 )
1,
b101 (
1"
#100
0"
#110
b110 !
b110 )
1*
b110 (
1"
#120
0"
#130
b111 !
b111 )
0+
b111 (
1"
#140
0,
0*
b0 (
b0 !
b0 )
1%
0"
