counter/down counter/downcounter.v
module downcounter
 #( 
    parameter data_width = 4 
  )

  (
    input wire clk,
    input wire load_en,
    input wire reset,
    input wire [data_width-1:0] d,
    output reg [data_width-1:0] q
  );

  always @(posedge reset, posedge clk)
    begin
        if(reset)

         q <= 4'b0000;

        else if(load_en)
         
         q <= d;
        
        else
         q <= q - 1'b1;
    end
endmodule

counter/down counter/downcounter_tb.v
`timescale 1ns/1ns

module downcounter_tb;
 reg clk;
 reg load_en;
 reg reset;
 reg [3:0] d;
 wire [3:0] q;

downcounter circ1(.clk(clk),.reset(reset),.load_en(load_en),.d(d),.q(q));

always begin
    clk = ~clk;
    #10;
end

initial begin
    $dumpfile("test.vcd");
    $dumpvars(0,downcounter_tb);
    
    clk <= 0;
    load_en <= 0;
    reset <= 1;
    

    #20;
    reset <= 0;
    #20;
    load_en <= 1;
    d <= 4'b1011;
    #20;
    load_en <= 0;
    #20;
    #20;
    #20;
    reset <= 1;
    #20;
    #20;
    #20;
    $finish;
end

initial begin 
    $monitor("time = %0t, clk = %b, reset = %b, load_en = %b, d = %b, q = %b",$time,clk,reset,load_en,d,q);
end
endmodule

counter/down counter/test.vcd
$date
	Thu Jul 11 23:58:32 2024
$end
$version
	Icarus Verilog
$end
$timescale
	1ns
$end
$scope module downcounter_tb $end
$var wire 4 ! q [3:0] $end
$var reg 1 " clk $end
$var reg 4 # d [3:0] $end
$var reg 1 $ load_en $end
$var reg 1 % reset $end
$scope module circ1 $end
$var wire 1 " clk $end
$var wire 4 & d [3:0] $end
$var wire 1 $ load_en $end
$var wire 1 % reset $end
$var parameter 32 ' data_width $end
$var reg 4 ( q [3:0] $end
$upscope $end
$upscope $end
$enddefinitions $end
$comment Show the parameter values. $end
$dumpall
b100 '
$end
#0
$dumpvars
b0 (
bx &
1%
0$
bx #
0"
b0 !
$end
#10
1"
#20
0%
0"
#30
b1111 !
b1111 (
1"
#40
b1011 #
b1011 &
1$
0"
#50
b1011 !
b1011 (
1"
#60
0$
0"
#70
b1010 !
b1010 (
1"
#80
0"
#90
b1001 !
b1001 (
1"
#100
0"
#110
b1000 !
b1000 (
1"
#120
b0 !
b0 (
1%
0"
