Laundry_Controller/laundry_controller_fsm.v
module laundry_controller_fsm( 
		input wire clk, reset, start,
		input wire [3:0] req_laundry, send,
		input wire count_eq10, count_eq50,
                 
		output reg [2:0] at_floor,
		output reg wash_done,clear);
			
		reg [2:0] pstate, nstate;

                parameter [2:0] IDLE = 3'b000,
				FLOOR_1 = 3'b001,
				FLOOR_2 = 3'b010,
				FLOOR_3 = 3'b011,
				FLOOR_4 = 3'b100,
				WASHING = 3'b101,
                WASHING_DONE = 3'b110; 
		

 			always @(*) begin : NSOL    
			  	begin : NSL
					case(pstate)

						IDLE : nstate = start ? 
									(req_laundry[3]? FLOOR_4 
								    	: (req_laundry[2]? FLOOR_3 
	                                    : (req_laundry[1]? FLOOR_2
                                        : (req_laundry[0]? FLOOR_1 : IDLE))))
								    	: IDLE; 
						
						FLOOR_4	: nstate = send[3] ?
									(req_laundry[2] ? FLOOR_3
									: (req_laundry[1] ? FLOOR_2
									: (req_laundry[0] ? FLOOR_1 : WASHING)))
									: (count_eq10 ? FLOOR_3 : FLOOR_4);
					       
						FLOOR_3 : nstate = send[2] ? 
									(req_laundry[1] ? FLOOR_2
									: (req_laundry[0] ? FLOOR_1 : WASHING))
									: (count_eq10 ? FLOOR_2 : FLOOR_3);
					     
						FLOOR_2 : nstate = send[1] ?
									(req_laundry[0] ? FLOOR_1 : WASHING)
									: (count_eq10 ? FLOOR_1 :FLOOR_2);
						
						FLOOR_1 : nstate = send[0] ? WASHING 
									: (count_eq10 ? FLOOR_1 : WASHING);
						
						WASHING : nstate = count_eq50 ? WASHING_DONE : WASHING;
                                                
						WASHING_DONE : nstate = IDLE;  

						default : nstate = 3'bx;

					endcase
                              end

			      begin : OL
                    case(pstate)
						
					    	IDLE :  begin
								clear = 1'b1;
								at_floor = 3'b101;
								wash_done = 1'b0;
							end
                                                
					      FLOOR_4 : begin
							    clear = count_eq10 | send[3];
								at_floor = 3'b100;
								wash_done = 1'b0;
							end
					     
					      FLOOR_3 : begin
							    clear = count_eq10 | send[2];
								at_floor = 3'b011;
								wash_done = 1'b0;
							end

					     FLOOR_2 : begin
							    clear = count_eq10 | send[1];
								at_floor = 3'b010;
								wash_done = 1'b0;
						       end

					     FLOOR_1 : begin
							    clear = count_eq10 | send[0];
								at_floor = 3'b001;
								wash_done = 1'b0;
						       end
				
					    WASHING :  begin
							    clear = count_eq50;
								at_floor = 3'b101;
								wash_done = 1'b0;
						       end
								
					 WASHING_DONE: begin
						        clear = 1'b1;
								at_floor = 3'b000;
								wash_done = 1'b1;
						       end

				        default : begin
							    clear = 1'bx;
								at_floor = 3'bx;
								wash_done = 1'bx;
						       end
				    endcase
			  end
			end

		    always @(posedge clk or negedge reset) begin : PSR 
				begin
				    if(~reset) begin
					 pstate <= IDLE;
				    end
				    
			        else begin
					 pstate <= nstate;
                    end
                end	
			end	
					   			
endmodule

Laundry_Controller/comparator.v
module comparator(
    input wire [5:0] count,
    output wire count_eq10, count_eq50);

        assign count_eq10 = count == 10;
        assign count_eq50 = count == 50;
endmodule

Laundry_Controller/counter.v
module counter (
    input wire clk, reset, clear,
    output reg [5:0] count);
 
        always @(posedge clk or negedge reset) begin
                  if(~reset) begin
                      count <= 6'b000000;
                    end
                  else begin
                      count <= clear ? 6'b000000 :  count + 1'b1;
                    end
        end
endmodule

Laundry_Controller/top.v
module top (
    input wire clk, reset, start,
    input wire [3:0]req_laundry, send,

    output wire [2:0] at_floor,
    output wire wash_done);

    wire [5:0] count_2_comp;
    wire comp_2_fsm_10, comp_2_fsm_50,clear;

    
        counter count1 (.clk(clk), 
                            .reset(reset), 
                            .clear(clear), 
                            .count(count_2_comp));
            
        comparator comp1 (.count(count_2_comp),
                              .count_eq10(comp_2_fsm_10),
                              .count_eq50(comp_2_fsm_50));

        laundry_controller_fsm fsm (.clk(clk),
                                    .reset(reset),
                                    .start(start),
                                    .req_laundry(req_laundry),
                                    .send(send),
                                    .count_eq10(comp_2_fsm_10),
                                    .count_eq50(comp_2_fsm_50),
                                    .at_floor(at_floor),
                                    .wash_done(wash_done),
                                    .clear(clear));
endmodule

Laundry_Controller/top_tb.sv
`timescale 1ns/1ns
module top_tb;
        reg clk, reset, start;
        reg [3:0] req, send;
        wire [2:0] at_floor;
        wire wash_done;

    top DUT(
        .clk(clk),
        .reset(reset),
        .start(start),
        .req_laundry(req),
        .send(send),
        .at_floor(at_floor),
        .wash_done(wash_done));

    initial begin 
        clk  = 0;
        forever #5 clk = ~clk;
    end


    initial begin
        reset <= 0;
        req <= 4'b0000;
        send <= 4'b0000;
        start <= 0;

        @(negedge clk);
            reset <= 1;
        
        @(negedge clk);
            start <= 1;
            req <= 4'b1100;

        repeat(3)  @(negedge clk);
             send <= 4'b1000;
        
        repeat(6)  @(negedge clk);
             send <= 4'b0001;

        @(negedge clk);
             req <= 4'b1000;
        
        repeat(100) @(negedge clk);
             $finish();
    end
endmodule

Laundry_Controller/test.vcd
$date
	Sat Jul 20 11:53:43 2024
$end
$version
	Icarus Verilog
$end
$timescale
	1ns
$end
$scope module top_tb $end
$var wire 1 ! wash_done $end
$var wire 3 " at_floor [2:0] $end
$var reg 1 # clk $end
$var reg 4 $ req [3:0] $end
$var reg 1 % reset $end
$var reg 4 & send [3:0] $end
$var reg 1 ' start $end
$scope module DUT $end
$var wire 1 # clk $end
$var wire 4 ( req_laundry [3:0] $end
$var wire 1 % reset $end
$var wire 4 ) send [3:0] $end
$var wire 1 ' start $end
$var wire 1 ! wash_done $end
$var wire 6 * count_2_comp [5:0] $end
$var wire 1 + comp_2_fsm_50 $end
$var wire 1 , comp_2_fsm_10 $end
$var wire 1 - clear $end
$var wire 3 . at_floor [2:0] $end
$scope module comp1 $end
$var wire 1 + count_eq50 $end
$var wire 1 , count_eq10 $end
$var wire 6 / count [5:0] $end
$upscope $end
$scope module count1 $end
$var wire 1 # clk $end
$var wire 1 % reset $end
$var wire 1 - clear $end
$var reg 6 0 count [5:0] $end
$upscope $end
$scope module fsm $end
$var wire 1 # clk $end
$var wire 1 , count_eq10 $end
$var wire 1 + count_eq50 $end
$var wire 4 1 req_laundry [3:0] $end
$var wire 1 % reset $end
$var wire 4 2 send [3:0] $end
$var wire 1 ' start $end
$var parameter 3 3 FLOOR_1 $end
$var parameter 3 4 FLOOR_2 $end
$var parameter 3 5 FLOOR_3 $end
$var parameter 3 6 FLOOR_4 $end
$var parameter 3 7 IDLE $end
$var parameter 3 8 WASHING $end
$var parameter 3 9 WASHING_DONE $end
$var reg 3 : at_floor [2:0] $end
$var reg 1 - clear $end
$var reg 3 ; nstate [2:0] $end
$var reg 3 < pstate [2:0] $end
$var reg 1 ! wash_done $end
$scope begin NSOL $end
$scope begin NSL $end
$upscope $end
$scope begin OL $end
$upscope $end
$upscope $end
$scope begin PSR $end
$upscope $end
$upscope $end
$upscope $end
$upscope $end
$enddefinitions $end
$comment Show the parameter values. $end
$dumpall
b110 9
b101 8
b0 7
b100 6
b11 5
b10 4
b1 3
$end
#0
$dumpvars
b0 <
b0 ;
b101 :
b0 2
b0 1
b0 0
b0 /
b101 .
1-
0,
0+
b0 *
b0 )
b0 (
0'
b0 &
0%
b0 $
0#
b101 "
0!
$end
#5
1#
#10
0#
#15
1#
#20
1%
0#
#25
1#
#30
b1001 $
b1001 (
b1001 1
0#
#35
1#
#40
b100 ;
1'
0#
#45
b100 "
b100 .
b100 :
0-
b100 <
1#
#50
0#
#55
b1 *
b1 /
b1 0
1#
#60
0#
#65
b10 *
b10 /
b10 0
1#
#70
0#
#75
b11 *
b11 /
b11 0
1#
#80
0#
#85
b100 *
b100 /
b100 0
1#
#90
0#
#95
b101 *
b101 /
b101 0
1#
#100
0#
#105
b110 *
b110 /
b110 0
1#
#110
0#
#115
b111 *
b111 /
b111 0
1#
#120
b1000 $
b1000 (
b1000 1
0#
#125
b1000 *
b1000 /
b1000 0
1#
#130
0#
#135
b1001 *
b1001 /
b1001 0
1#
#140
0#
#145
1-
b11 ;
1,
b1010 *
b1010 /
b1010 0
1#
#150
0#
#155
b11 "
b11 .
b11 :
0-
b11 <
0,
b0 *
b0 /
b0 0
1#
#160
0#
#165
b1 *
b1 /
b1 0
1#
#170
0#
#175
b10 *
b10 /
b10 0
1#
#180
0#
#185
b11 *
b11 /
b11 0
1#
#190
0#
#195
b100 *
b100 /
b100 0
1#
#200
0#
#205
b101 *
b101 /
b101 0
1#
#210
0#
#215
b110 *
b110 /
b110 0
1#
#220
0#
#225
b111 *
b111 /
b111 0
1#
#230
0#
#235
b1000 *
b1000 /
b1000 0
1#
#240
0#
#245
b1001 *
b1001 /
b1001 0
1#
#250
0#
#255
1-
b10 ;
1,
b1010 *
b1010 /
b1010 0
1#
#260
0#
#265
b10 "
b10 .
b10 :
0-
b10 <
0,
b0 *
b0 /
b0 0
1#
#270
0#
#275
b1 *
b1 /
b1 0
1#
#280
0#
#285
b10 *
b10 /
b10 0
1#
#290
0#
#295
b11 *
b11 /
b11 0
1#
#300
0#
#305
b100 *
b100 /
b100 0
1#
#310
0#
#315
b101 *
b101 /
b101 0
1#
#320
0#
#325
b110 *
b110 /
b110 0
1#
#330
0#
#335
b111 *
b111 /
b111 0
1#
#340
0#
#345
b1000 *
b1000 /
b1000 0
1#
#350
0#
#355
b1001 *
b1001 /
b1001 0
1#
#360
0#
#365
1-
b1 ;
1,
b1010 *
b1010 /
b1010 0
1#
#370
0#
#375
b1 "
b1 .
b1 :
0-
b101 ;
b1 <
0,
b0 *
b0 /
b0 0
1#
#380
0#
#385
b101 "
b101 .
b101 :
b101 <
b1 *
b1 /
b1 0
1#
#390
0#
#395
b10 *
b10 /
b10 0
1#
#400
0#
#405
b11 *
b11 /
b11 0
1#
#410
0#
#415
b100 *
b100 /
b100 0
1#
#420
0#
#425
b101 *
b101 /
b101 0
1#
#430
0#
#435
b110 *
b110 /
b110 0
1#
#440
0#
#445
b111 *
b111 /
b111 0
1#
#450
0#
#455
b1000 *
b1000 /
b1000 0
1#
#460
0#
#465
b1001 *
b1001 /
b1001 0
1#
#470
0#
#475
1,
b1010 *
b1010 /
b1010 0
1#
#480
0#
#485
0,
b1011 *
b1011 /
b1011 0
1#
#490
0#
#495
b1100 *
b1100 /
b1100 0
1#
#500
0#
#505
b1101 *
b1101 /
b1101 0
1#
#510
0#
#515
b1110 *
b1110 /
b1110 0
1#
#520
0#
#525
b1111 *
b1111 /
b1111 0
1#
#530
0#
#535
b10000 *
b10000 /
b10000 0
1#
#540
0#
#545
b10001 *
b10001 /
b10001 0
1#
#550
0#
#555
b10010 *
b10010 /
b10010 0
1#
#560
0#
#565
b10011 *
b10011 /
b10011 0
1#
#570
0#
#575
b10100 *
b10100 /
b10100 0
1#
#580
0#
#585
b10101 *
b10101 /
b10101 0
1#
#590
0#
#595
b10110 *
b10110 /
b10110 0
1#
#600
0#
#605
b10111 *
b10111 /
b10111 0
1#
#610
0#
#615
b11000 *
b11000 /
b11000 0
1#
#620
0#
#625
b11001 *
b11001 /
b11001 0
1#
#630
0#
#635
b11010 *
b11010 /
b11010 0
1#
#640
0#
#645
b11011 *
b11011 /
b11011 0
1#
#650
0#
#655
b11100 *
b11100 /
b11100 0
1#
#660
0#
#665
b11101 *
b11101 /
b11101 0
1#
#670
0#
#675
b11110 *
b11110 /
b11110 0
1#
#680
0#
#685
b11111 *
b11111 /
b11111 0
1#
#690
0#
#695
b100000 *
b100000 /
b100000 0
1#
#700
0#
#705
b100001 *
b100001 /
b100001 0
1#
#710
0#
#715
b100010 *
b100010 /
b100010 0
1#
#720
0#
#725
b100011 *
b100011 /
b100011 0
1#
#730
0#
#735
b100100 *
b100100 /
b100100 0
1#
#740
0#
#745
b100101 *
b100101 /
b100101 0
1#
#750
0#
#755
b100110 *
b100110 /
b100110 0
1#
#760
0#
#765
b100111 *
b100111 /
b100111 0
1#
#770
0#
#775
b101000 *
b101000 /
b101000 0
1#
#780
0#
#785
b101001 *
b101001 /
b101001 0
1#
#790
0#
#795
b101010 *
b101010 /
b101010 0
1#
#800
0#
#805
b101011 *
b101011 /
b101011 0
1#
#810
0#
#815
b101100 *
b101100 /
b101100 0
1#
#820
0#
#825
b101101 *
b101101 /
b101101 0
1#
#830
0#
#835
b101110 *
b101110 /
b101110 0
1#
#840
0#
#845
b101111 *
b101111 /
b101111 0
1#
#850
0#
#855
b110000 *
b110000 /
b110000 0
1#
#860
0#
#865
b110001 *
b110001 /
b110001 0
1#
#870
0#
#875
1-
b110 ;
1+
b110010 *
b110010 /
b110010 0
1#
#880
0#
#885
1!
b0 "
b0 .
b0 :
b0 ;
b110 <
0+
b0 *
b0 /
b0 0
1#
#890
0#
#895
0!
b101 "
b101 .
b101 :
b100 ;
b0 <
1#
#900
0#
#905
b100 "
b100 .
b100 :
0-
b100 <
1#
#910
0#
#915
b1 *
b1 /
b1 0
1#
#920
0#
#925
b10 *
b10 /
b10 0
1#
#930
0#
#935
b11 *
b11 /
b11 0
1#
#940
0#
#945
b100 *
b100 /
b100 0
1#
#950
0#
#955
b101 *
b101 /
b101 0
1#
#960
0#
#965
b110 *
b110 /
b110 0
1#
#970
0#
#975
b111 *
b111 /
b111 0
1#
#980
0#
#985
b1000 *
b1000 /
b1000 0
1#
#990
0#
#995
b1001 *
b1001 /
b1001 0
1#
#1000
0#
#1005
1-
b11 ;
1,
b1010 *
b1010 /
b1010 0
1#
#1010
0#
#1015
b11 "
b11 .
b11 :
0-
b11 <
0,
b0 *
b0 /
b0 0
1#
#1020
0#
#1025
b1 *
b1 /
b1 0
1#
#1030
0#
#1035
b10 *
b10 /
b10 0
1#
#1040
0#
#1045
b11 *
b11 /
b11 0
1#
#1050
0#
#1055
b100 *
b100 /
b100 0
1#
#1060
0#
#1065
b101 *
b101 /
b101 0
1#
#1070
0#
#1075
b110 *
b110 /
b110 0
1#
#1080
0#
#1085
b111 *
b111 /
b111 0
1#
#1090
0#
#1095
b1000 *
b1000 /
b1000 0
1#
#1100
0#
#1105
b1001 *
b1001 /
b1001 0
1#
#1110
0#
#1115
1-
b10 ;
1,
b1010 *
b1010 /
b1010 0
1#
#1120
0#
#1125
b10 "
b10 .
b10 :
0-
b10 <
0,
b0 *
b0 /
b0 0
1#
#1130
0#
#1135
b1 *
b1 /
b1 0
1#
#1140
0#
#1145
b10 *
b10 /
b10 0
1#
#1150
0#
#1155
b11 *
b11 /
b11 0
1#
#1160
0#
#1165
b100 *
b100 /
b100 0
1#
#1170
0#
#1175
b101 *
b101 /
b101 0
1#
#1180
0#
#1185
b110 *
b110 /
b110 0
1#
#1190
0#
#1195
b111 *
b111 /
b111 0
1#
#1200
0#
#1205
b1000 *
b1000 /
b1000 0
1#
#1210
0#
#1215
b1001 *
b1001 /
b1001 0
1#
#1220
0#
#1225
1-
b1 ;
1,
b1010 *
b1010 /
b1010 0
1#
#1230
0#
#1235
b1 "
b1 .
b1 :
0-
b101 ;
b1 <
0,
b0 *
b0 /
b0 0
1#
#1240
0#
#1245
b101 "
b101 .
b101 :
b101 <
b1 *
b1 /
b1 0
1#
#1250
0#
#1255
b10 *
b10 /
b10 0
1#
#1260
0#
#1265
b11 *
b11 /
b11 0
1#
#1270
0#
#1275
b100 *
b100 /
b100 0
1#
#1280
0#
#1285
b101 *
b101 /
b101 0
1#
#1290
0#
#1295
b110 *
b110 /
b110 0
1#
#1300
0#
#1305
b111 *
b111 /
b111 0
1#
#1310
0#
#1315
b1000 *
b1000 /
b1000 0
1#
#1320
0#
#1325
b1001 *
b1001 /
b1001 0
1#
#1330
0#
#1335
1,
b1010 *
b1010 /
b1010 0
1#
#1340
0#
#1345
0,
b1011 *
b1011 /
b1011 0
1#
#1350
0#
#1355
b1100 *
b1100 /
b1100 0
1#
#1360
0#
#1365
b1101 *
b1101 /
b1101 0
1#
#1370
0#
#1375
b1110 *
b1110 /
b1110 0
1#
#1380
0#
#1385
b1111 *
b1111 /
b1111 0
1#
#1390
0#
#1395
b10000 *
b10000 /
b10000 0
1#
#1400
0#
#1405
b10001 *
b10001 /
b10001 0
1#
#1410
0#
#1415
b10010 *
b10010 /
b10010 0
1#
#1420
0#
#1425
b10011 *
b10011 /
b10011 0
1#
#1430
0#
#1435
b10100 *
b10100 /
b10100 0
1#
#1440
0#
#1445
b10101 *
b10101 /
b10101 0
1#
#1450
0#
#1455
b10110 *
b10110 /
b10110 0
1#
#1460
0#
#1465
b10111 *
b10111 /
b10111 0
1#
#1470
0#
#1475
b11000 *
b11000 /
b11000 0
1#
#1480
0#
#1485
b11001 *
b11001 /
b11001 0
1#
#1490
0#
#1495
b11010 *
b11010 /
b11010 0
1#
#1500
0#
#1505
b11011 *
b11011 /
b11011 0
1#
#1510
0#
#1515
b11100 *
b11100 /
b11100 0
1#
#1520
0#
#1525
b11101 *
b11101 /
b11101 0
1#
#1530
0#
#1535
b11110 *
b11110 /
b11110 0
1#
#1540
0#
#1545
b11111 *
b11111 /
b11111 0
1#
#1550
0#
#1555
b100000 *
b100000 /
b100000 0
1#
#1560
0#
#1565
b100001 *
b100001 /
b100001 0
1#
#1570
0#
#1575
b100010 *
b100010 /
b100010 0
1#
#1580
0#
#1585
b100011 *
b100011 /
b100011 0
1#
#1590
0#
#1595
b100100 *
b100100 /
b100100 0
1#
#1600
0#
#1605
b100101 *
b100101 /
b100101 0
1#
#1610
0#
#1615
b100110 *
b100110 /
b100110 0
1#
#1620
0#
#1625
b100111 *
b100111 /
b100111 0
1#
#1630
0#
#1635
b101000 *
b101000 /
b101000 0
1#
#1640
0#
#1645
b101001 *
b101001 /
b101001 0
1#
#1650
0#
#1655
b101010 *
b101010 /
b101010 0
1#
#1660
0#
#1665
b101011 *
b101011 /
b101011 0
1#
#1670
0#
#1675
b101100 *
b101100 /
b101100 0
1#
#1680
0#
#1685
b101101 *
b101101 /
b101101 0
1#
#1690
0#
#1695
b101110 *
b101110 /
b101110 0
1#
#1700
0#
#1705
b101111 *
b101111 /
b101111 0
1#
#1710
0#
#1715
b110000 *
b110000 /
b110000 0
1#
#1720
0#
#1725
b110001 *
b110001 /
b110001 0
1#
#1730
0#
#1735
1-
b110 ;
1+
b110010 *
b110010 /
b110010 0
1#
#1740
0#
#1745
1!
b0 "
b0 .
b0 :
b0 ;
b110 <
0+
b0 *
b0 /
b0 0
1#
#1750
0#
#1755
0!
b101 "
b101 .
b101 :
b100 ;
b0 <
1#
#1760
0#
#1765
b100 "
b100 .
b100 :
0-
b100 <
1#
#1770
0#
#1775
b1 *
b1 /
b1 0
1#
#1780
0#
#1785
b10 *
b10 /
b10 0
1#
#1790
0#
#1795
b11 *
b11 /
b11 0
1#
#1800
0#
#1805
b100 *
b100 /
b100 0
1#
#1810
0#
#1815
b101 *
b101 /
b101 0
1#
#1820
0#
#1825
b110 *
b110 /
b110 0
1#
#1830
0#
#1835
b111 *
b111 /
b111 0
1#
#1840
0#
#1845
b1000 *
b1000 /
b1000 0
1#
#1850
0#
#1855
b1001 *
b1001 /
b1001 0
1#
#1860
0#
#1865
1-
b11 ;
1,
b1010 *
b1010 /
b1010 0
1#
#1870
0#
#1875
b11 "
b11 .
b11 :
0-
b11 <
0,
b0 *
b0 /
b0 0
1#
#1880
0#
#1885
b1 *
b1 /
b1 0
1#
#1890
0#
#1895
b10 *
b10 /
b10 0
1#
#1900
0#
#1905
b11 *
b11 /
b11 0
1#
#1910
0#
#1915
b100 *
b100 /
b100 0
1#
#1920
0#
#1925
b101 *
b101 /
b101 0
1#
#1930
0#
#1935
b110 *
b110 /
b110 0
1#
#1940
0#
#1945
b111 *
b111 /
b111 0
1#
#1950
0#
#1955
b1000 *
b1000 /
b1000 0
1#
#1960
0#
#1965
b1001 *
b1001 /
b1001 0
1#
#1970
0#
#1975
1-
b10 ;
1,
b1010 *
b1010 /
b1010 0
1#
#1980
0#
#1985
b10 "
b10 .
b10 :
0-
b10 <
0,
b0 *
b0 /
b0 0
1#
#1990
0#
#1995
b1 *
b1 /
b1 0
1#
#2000
0#
#2005
b10 *
b10 /
b10 0
1#
#2010
0#
#2015
b11 *
b11 /
b11 0
1#
#2020
0#
#2025
b100 *
b100 /
b100 0
1#
#2030
0#
#2035
b101 *
b101 /
b101 0
1#
#2040
0#
#2045
b110 *
b110 /
b110 0
1#
#2050
0#
#2055
b111 *
b111 /
b111 0
1#
#2060
0#
#2065
b1000 *
b1000 /
b1000 0
1#
#2070
0#
#2075
b1001 *
b1001 /
b1001 0
1#
#2080
0#
#2085
1-
b1 ;
1,
b1010 *
b1010 /
b1010 0
1#
#2090
0#
#2095
b1 "
b1 .
b1 :
0-
b101 ;
b1 <
0,
b0 *
b0 /
b0 0
1#
#2100
0#
#2105
b101 "
b101 .
b101 :
b101 <
b1 *
b1 /
b1 0
1#
#2110
0#
#2115
b10 *
b10 /
b10 0
1#
